litebaseio/__init__.py
litebaseio/client.py
litebaseio/models.py
litebaseio/storage.py
litebaseio/stream.py
litebaseio-0.0.5.dist-info/METADATA
litebaseio-0.0.5.dist-info/WHEEL
litebaseio-0.0.5.dist-info/licenses/LICENSE
litebaseio-0.0.5.dist-info/RECORD
