Metadata-Version: 2.4
Name: litebaseio
Version: 0.0.5
Summary: Python SDK for Litebase Storage and Stream APIs
Project-URL: Homepage, https://litebase.io
Project-URL: Repository, https://github.com/litebaseio/litebase-py
Author-email: Litebase <support@litebase.io>
License: MIT License
License-File: LICENSE
Requires-Python: >=3.8
Requires-Dist: httpx>=0.24.0
Requires-Dist: pydantic>=2.0
